IonicZhongwenWendang/README.md
IonicZhongwenWendang/__init__.py
IonicZhongwenWendang/__main__.py
IonicZhongwenWendang/file.epub
IonicZhongwenWendang/index.html
IonicZhongwenWendang/css/__init__.py
IonicZhongwenWendang/css/annotations.css
IonicZhongwenWendang/css/main.css
IonicZhongwenWendang/css/normalize.css
IonicZhongwenWendang/css/popup.css
IonicZhongwenWendang/font/__init__.py
IonicZhongwenWendang/font/fontello.eot
IonicZhongwenWendang/font/fontello.svg
IonicZhongwenWendang/font/fontello.ttf
IonicZhongwenWendang/font/fontello.woff
IonicZhongwenWendang/img/__init__.py
IonicZhongwenWendang/img/annotator-glyph-sprite.png
IonicZhongwenWendang/img/annotator-icon-sprite.png
IonicZhongwenWendang/img/apple-touch-icon.png
IonicZhongwenWendang/img/cancelfullscreen.png
IonicZhongwenWendang/img/close.png
IonicZhongwenWendang/img/fullscreen.png
IonicZhongwenWendang/img/loader.gif
IonicZhongwenWendang/img/menu-icon.png
IonicZhongwenWendang/img/save.png
IonicZhongwenWendang/img/saved.png
IonicZhongwenWendang/img/settings-s.png
IonicZhongwenWendang/img/settings.png
IonicZhongwenWendang/img/star.png
IonicZhongwenWendang/js/__init__.py
IonicZhongwenWendang/js/epub.js
IonicZhongwenWendang/js/epub.min.js
IonicZhongwenWendang/js/epub.min.map
IonicZhongwenWendang/js/hooks.min.js
IonicZhongwenWendang/js/hooks.min.map
IonicZhongwenWendang/js/reader.js
IonicZhongwenWendang/js/reader.js.map
IonicZhongwenWendang/js/reader.min.js
IonicZhongwenWendang/js/reader.min.map
IonicZhongwenWendang/js/hooks/__init__.py
IonicZhongwenWendang/js/hooks/extensions/__init__.py
IonicZhongwenWendang/js/hooks/extensions/highlight.js
IonicZhongwenWendang/js/libs/__init__.py
IonicZhongwenWendang/js/libs/jquery.min.js
IonicZhongwenWendang/js/libs/localforage.min.js
IonicZhongwenWendang/js/libs/screenfull.js
IonicZhongwenWendang/js/libs/screenfull.min.js
IonicZhongwenWendang/js/libs/zip.min.js
IonicZhongwenWendang/js/plugins/__init__.py
IonicZhongwenWendang/js/plugins/hypothesis.js
ionic_zhongwen_wendang-2024.3.1.0.dist-info/METADATA
ionic_zhongwen_wendang-2024.3.1.0.dist-info/WHEEL
ionic_zhongwen_wendang-2024.3.1.0.dist-info/entry_points.txt
ionic_zhongwen_wendang-2024.3.1.0.dist-info/top_level.txt
ionic_zhongwen_wendang-2024.3.1.0.dist-info/RECORD
